spectrogrammer/__init__.py
spectrogrammer/spectrogrammer.py
spectrogrammer-1.0.1.dist-info/LICENSE
spectrogrammer-1.0.1.dist-info/METADATA
spectrogrammer-1.0.1.dist-info/WHEEL
spectrogrammer-1.0.1.dist-info/top_level.txt
spectrogrammer-1.0.1.dist-info/RECORD
